[
  {
    "username": "troubleshooter",
    "success": 3,
    "total": 3,
    "time": 10,
    "numbers": 3,
    "autoHide": 0,
    "score": 556,
    "date": "2025-06-18T17:54:55.538Z"
  },
  {
    "username": "troubleshooter",
    "success": 3,
    "total": 3,
    "time": 10,
    "numbers": 3,
    "autoHide": 1000,
    "score": 456,
    "date": "2025-06-18T17:56:26.728Z"
  },
  {
    "username": "troubleshooter",
    "success": 3,
    "total": 3,
    "time": 10,
    "numbers": 3,
    "autoHide": 750,
    "score": 506,
    "date": "2025-06-18T17:56:54.338Z"
  },
  {
    "username": "troubleshooter",
    "success": 3,
    "total": 3,
    "time": 11,
    "numbers": 3,
    "autoHide": 1000,
    "score": 631,
    "date": "2025-06-18T17:58:04.891Z"
  }
]